labelpt/__init__.py
labelpt/run.py
labelpt/app/__init__.py
labelpt/app/image_process.py
labelpt/app/presenter/__init__.py
labelpt/app/presenter/initial_setting_presenter.py
labelpt/app/presenter/segmentation_presenter.py
labelpt/web/build/asset-manifest.json
labelpt/web/build/favicon.ico
labelpt/web/build/index.html
labelpt/web/build/logo192.png
labelpt/web/build/logo512.png
labelpt/web/build/manifest.json
labelpt/web/build/robots.txt
labelpt/web/build/static/css/main.fb0ce907.chunk.css
labelpt/web/build/static/css/main.fb0ce907.chunk.css.map
labelpt/web/build/static/js/2.9902d683.chunk.js
labelpt/web/build/static/js/2.9902d683.chunk.js.LICENSE.txt
labelpt/web/build/static/js/2.9902d683.chunk.js.map
labelpt/web/build/static/js/3.580b34e0.chunk.js
labelpt/web/build/static/js/3.580b34e0.chunk.js.map
labelpt/web/build/static/js/main.77c88601.chunk.js
labelpt/web/build/static/js/main.77c88601.chunk.js.map
labelpt/web/build/static/js/runtime-main.ab190108.js
labelpt/web/build/static/js/runtime-main.ab190108.js.map
test/__init__.py
test/test_image_process.py
test/test_initial_setting_presenter.py
test/test_segmentation_presenter.py
labelpt-0.1.1.dist-info/LICENSE
labelpt-0.1.1.dist-info/METADATA
labelpt-0.1.1.dist-info/WHEEL
labelpt-0.1.1.dist-info/entry_points.txt
labelpt-0.1.1.dist-info/top_level.txt
labelpt-0.1.1.dist-info/RECORD
