Metadata-Version: 2.1
Name: labelpt
Version: 0.1.1
Summary: Annotation tool of image segmentation.
Home-page: https://github.com/pei223/labelpt
Author: pei223
Author-email: peidparc@gmail.com
License: MIT
Keywords: image-segmentation annotation annotation-tool
Platform: UNKNOWN
Classifier: License :: OSI Approved :: MIT License
Classifier: Programming Language :: Python :: 3.7
Requires-Dist: eel
Requires-Dist: Pillow
Requires-Dist: numpy
